{
  "typography": {
    "body": {
      "fontFamily": { "$value": "{typography.fontFamily.sans}", "$type": "fontFamily" },
      "fontSize":   { "$value": "{typography.fontSize.base}",   "$type": "dimension" },
      "fontWeight": { "$value": "{typography.fontWeight.regular}", "$type": "fontWeight" },
      "lineHeight": { "$value": "{typography.lineHeight.normal}", "$type": "number" }
    },
    "label": {
      "fontFamily": { "$value": "{typography.fontFamily.sans}", "$type": "fontFamily" },
      "fontSize":   { "$value": "{typography.fontSize.sm}",    "$type": "dimension" },
      "fontWeight": { "$value": "{typography.fontWeight.medium}", "$type": "fontWeight" },
      "lineHeight": { "$value": "{typography.lineHeight.tight}", "$type": "number" }
    },
    "heading": {
      "fontFamily": { "$value": "{typography.fontFamily.sans}", "$type": "fontFamily" },
      "fontWeight": { "$value": "{typography.fontWeight.bold}", "$type": "fontWeight" },
      "lineHeight": { "$value": "{typography.lineHeight.tight}", "$type": "number" }
    },
    "code": {
      "fontFamily": { "$value": "{typography.fontFamily.mono}", "$type": "fontFamily" },
      "fontSize":   { "$value": "{typography.fontSize.sm}",    "$type": "dimension" }
    }
  }
}
